binance_futures_mcp-1.2.1.dist-info/licenses/LICENSE
binance_mcp/__init__.py
binance_mcp/__main__.py
binance_mcp/client.py
binance_mcp/config.py
binance_mcp/handlers.py
binance_mcp/server.py
binance_mcp/tools.py
binance_futures_mcp-1.2.1.dist-info/METADATA
binance_futures_mcp-1.2.1.dist-info/WHEEL
binance_futures_mcp-1.2.1.dist-info/entry_points.txt
binance_futures_mcp-1.2.1.dist-info/top_level.txt
binance_futures_mcp-1.2.1.dist-info/RECORD
