Metadata-Version: 2.4
Name: binance_futures_mcp
Version: 1.2.1
Summary: A Model Context Protocol server for Binance Futures API with comprehensive trading tools including TP/SL management
Home-page: https://github.com/alexcandrabersiva/bin-mcp
Author: Binance MCP Server
License-Expression: MIT
Project-URL: Homepage, https://github.com/alexcandrabersiva/bin-mcp
Project-URL: Repository, https://github.com/alexcandrabersiva/bin-mcp.git
Project-URL: Issues, https://github.com/alexcandrabersiva/bin-mcp/issues
Keywords: mcp,binance,trading,futures,api,model-context-protocol
Classifier: Development Status :: 4 - Beta
Classifier: Intended Audience :: Developers
Classifier: Programming Language :: Python :: 3
Classifier: Programming Language :: Python :: 3.8
Classifier: Programming Language :: Python :: 3.9
Classifier: Programming Language :: Python :: 3.10
Classifier: Programming Language :: Python :: 3.11
Classifier: Programming Language :: Python :: 3.12
Classifier: Topic :: Software Development :: Libraries :: Python Modules
Classifier: Topic :: Office/Business :: Financial :: Investment
Requires-Python: >=3.8
License-File: LICENSE
Requires-Dist: mcp>=1.0.0
Requires-Dist: aiohttp>=3.8.0
Requires-Dist: pydantic>=2.0.0
Provides-Extra: dev
Requires-Dist: pytest>=7.0.0; extra == "dev"
Requires-Dist: pytest-asyncio>=0.21.0; extra == "dev"
Requires-Dist: black>=23.0.0; extra == "dev"
Requires-Dist: mypy>=1.0.0; extra == "dev"
Requires-Dist: ruff>=0.1.0; extra == "dev"
Dynamic: home-page
Dynamic: license-file
Dynamic: requires-python
